catsgmo/__init__.py
catsgmo/main.py
catsgmo/site/__init__.py
catsgmo/site/demo_stock_binary.py
catsgmo/worker/__init__.py
catsgmo/worker/demo_stock_binary.py
catsgmo/worker/output.py
catsgmo-0.3.1.dist-info/METADATA
catsgmo-0.3.1.dist-info/WHEEL
catsgmo-0.3.1.dist-info/entry_points.txt
catsgmo-0.3.1.dist-info/top_level.txt
catsgmo-0.3.1.dist-info/RECORD
