Metadata-Version: 2.1
Name: catsgmo
Version: 0.3.1
Summary: GMO証券のAPIです/API for click-sec.com
Home-page: https://finance.rescala.jp
Author: RV
Author-email: yo-maruya@rescala.jp
License: MIT
Project-URL: Bug Reports, https://github.com/rv-rescala/catsgmo/issues
Project-URL: Source, https://github.com/rv-rescala/catsgmo
Platform: UNKNOWN
Requires-Python: >=3.5
Requires-Dist: catscore
